gade/__init__.py
gade/__main__.py
gade/allocation.py
gade/analyzer.py
gade/benchmark.py
gade/cli.py
gade/config.py
gade/exceptions.py
gade/improve.py
gade/logging.py
gade/memory.py
gade/models.py
gade/refactor.py
gade/api/__init__.py
gade/api/server.py
gade/integrations/__init__.py
gade/integrations/langchain.py
gade/integrations/openai_tools.py
gade/llm/__init__.py
gade/llm/client.py
gade/llm/strategies.py
gade/mcp/__init__.py
gade/mcp/server.py
gade/output/__init__.py
gade/output/heatmap.py
gade/output/json_export.py
gade/signals/__init__.py
gade/signals/base.py
gade/signals/edit_churn.py
gade/signals/error_density.py
gade/signals/gradient.py
gade/signals/semantic_complexity.py
gade/signals/uncertainty.py
gade-0.2.2.dist-info/METADATA
gade-0.2.2.dist-info/WHEEL
gade-0.2.2.dist-info/entry_points.txt
gade-0.2.2.dist-info/RECORD
