Metadata-Version: 2.4
Name: gade
Version: 0.2.2
Summary: Gradient-Aware Development Environment - Allocate AI compute dynamically based on code difficulty
Author: GADE Team
License: MIT
Keywords: ai,cli,code-analysis,development,llm
Classifier: Development Status :: 3 - Alpha
Classifier: Environment :: Console
Classifier: Intended Audience :: Developers
Classifier: License :: OSI Approved :: MIT License
Classifier: Programming Language :: Python :: 3.11
Classifier: Programming Language :: Python :: 3.12
Classifier: Topic :: Software Development :: Quality Assurance
Requires-Python: >=3.11
Requires-Dist: click>=8.1.0
Requires-Dist: gitpython>=3.1.0
Requires-Dist: pydantic>=2.0.0
Requires-Dist: pyyaml>=6.0.0
Requires-Dist: rich>=13.0.0
Provides-Extra: all
Requires-Dist: fastapi>=0.100.0; extra == 'all'
Requires-Dist: langchain-core>=0.1.0; extra == 'all'
Requires-Dist: langchain>=0.1.0; extra == 'all'
Requires-Dist: litellm>=1.0.0; extra == 'all'
Requires-Dist: mcp>=0.1.0; extra == 'all'
Requires-Dist: structlog>=23.0.0; extra == 'all'
Requires-Dist: uvicorn>=0.20.0; extra == 'all'
Provides-Extra: api
Requires-Dist: fastapi>=0.100.0; extra == 'api'
Requires-Dist: uvicorn>=0.20.0; extra == 'api'
Provides-Extra: dev
Requires-Dist: mypy>=1.0.0; extra == 'dev'
Requires-Dist: pytest-cov>=4.0.0; extra == 'dev'
Requires-Dist: pytest>=7.0.0; extra == 'dev'
Requires-Dist: ruff>=0.1.0; extra == 'dev'
Provides-Extra: langchain
Requires-Dist: langchain-core>=0.1.0; extra == 'langchain'
Requires-Dist: langchain>=0.1.0; extra == 'langchain'
Provides-Extra: llm
Requires-Dist: litellm>=1.0.0; extra == 'llm'
Provides-Extra: mcp
Requires-Dist: mcp>=0.1.0; extra == 'mcp'
Provides-Extra: observability
Requires-Dist: structlog>=23.0.0; extra == 'observability'
